[1,["ecpdLyjvZBwrvm+cedCcQy","7a/QZLET9IDreTiBfRn2PD","b5aLcqyFpDwImThpq8HcsA","14uiZFrABGS4RvPuPblQ89","c0JDLYrFtKu5N3LcxbOkaD","63eQeORelDubgGkpjs1Am+","1fFw9PJJhJpoM6Op1IQAxa","3dZBaY311JEprlFWXk88gX","ccGNmvRohMBp4sxeTcKHLa","b1osQHBydErofPqKsPfLLE","5bb7MCgIBHjLpWOTn/ocpi","abT+5Hst5Ov4+W8q5fKqcb","bcCAu6o4tMGpXuly6zB+eA","84wwzuVaVKX4nj1+BY1J76","13gV0idiJDcY/QWVlyhxOo","32vlPPijNDSbnuiJYAcKKt","a1KAvcDKlH14kUUDlhKaqm","e2gFI6neRJKrBl6Y+QQw2c","c0Yy14kWBMeYNYYcrLHe96","97IqubjxpOh5rJPf9UtDcw","64dd1lcVxHe4HRMUe5sYLx","b6UYCoZUJD7K5uQgYPfGuU","9crR9zZK1I7ZyQnmPBl0Zh"],["node","_spriteFrame","_N$skeletonData","_parent","horBgSpriteFrame","verBgSpriteFrame","root","data"],[["cc.Node",["_name","_active","_components","_prefab","_contentSize","_parent","_children","_trs","_anchorPoint","_color"],1,9,4,5,1,2,7,5,5],["cc.Sprite",["_sizeMode","node","_materials","_spriteFrame"],2,1,3,6],["758eeabriBEx5OHRk59V0EH",["controlSize","ui_config","controlActive","controlSpriteFrame","node"],-1,1],["cc.PrefabInfo",["fileId","root","asset"],2,1,1],["cc.Label",["_string","_fontSize","_lineHeight","_enableWrapText","_N$verticalAlign","_N$overflow","_N$horizontalAlign","node","_materials"],-4,1,3],["ff4c25x0QRCFIiuws3/K2M1",["isAtlasType","atlasPath","spriteFrame","onlyInLanguages","node","params"],-1,1,9],["cc.Prefab",["_name","asyncLoadAssets"],1],["cc.Button",["zoomScale","_N$transition","node"],1,1],["cc.Layout",["_resize","_N$layoutType","node","_layoutSize"],1,1,5],["sp.Skeleton",["defaultSkin","defaultAnimation","_preCacheMode","premultipliedAlpha","_animationName","node","_materials","_N$skeletonData"],-2,1,3,6],["LangSpPraams",["language","scale","pos"],1,5],["cc.PolygonCollider",["node","points"],3,1,12],["b5439VrYJBCYKbdmfsjRxSA",["node","ui_btnRoom","horBgSpriteFrame","verBgSpriteFrame"],3,1,2,6,6],["5e08cHc8l1IJYs6o57eT/X4",["node"],3,1]],[[3,0,1,2,2],[0,0,5,2,3,4,7,2],[10,0,1,2,3],[1,1,2,3,1],[0,0,5,2,3,4,2],[4,0,1,2,3,6,4,5,7,8,8],[1,1,2,1],[9,0,1,2,3,4,5,6,7,6],[0,0,6,2,3,4,7,2],[2,2,3,0,1,4,5],[7,0,1,2,3],[5,0,1,2,4,5,4],[11,0,1,1],[0,0,1,5,2,3,4,3],[4,0,1,2,3,4,5,7,8,7],[5,0,1,2,3,4,5],[6,0,1,3],[0,0,6,2,3,4,2],[0,0,5,6,2,3,4,7,2],[0,0,5,2,3,4,8,7,2],[0,0,5,2,3,9,4,8,7,2],[0,0,5,6,2,3,4,8,7,2],[0,0,5,6,2,3,2],[0,0,1,5,6,2,3,4,7,3],[0,0,1,5,6,2,3,4,3],[1,0,1,2,3,2],[1,0,1,2,2],[2,2,0,1,4,4],[2,3,0,1,4,4],[3,1,2,1],[8,0,1,2,3,3],[12,0,1,2,3,1],[13,0,1]],[[16,"hall",true],[17,"hall",[-8,-9,-10,-11,-12,-13],[[31,-6,[-2,-3,-4,-5],57,58],[32,-7]],[29,-1,0],[5,1280,720]],[8,"ui_btnRoomType_4",[-15,-16,-17,-18,-19,-20],[[12,-14,[[[0,-54.5,100.5],[0,-179.5,-5.2],[0,-185.4,-24.1],[0,-17.6,-175],[0,6.6,-176.3],[0,93.6,-101.2],[0,121.1,-78.5],[0,157.7,-50.6],[0,183.2,-27.9],[0,185.8,-11.5],[0,113.3,52.4],[0,81.5,78.6],[0,59.5,150.8],[0,7.3,161]],8,8,8,8,8,8,8,8,8,8,8,8,8,8]]],[0,"08G8efI7xESakFEBmdHWGF",1,0],[5,400,390],[333.804,13.359,0,0,0,0,1,1,1,1]],[8,"ui_btnRoomType_3",[-22,-23,-24,-25,-26,-27],[[12,-21,[[[0,-7.4,122.4],[0,-137.6,9],[0,-137.6,-7.3],[0,-7.7,-118.9],[0,6.6,-117.4],[0,71.2,-64.1],[0,137.9,-5.5],[0,138.7,6.9],[0,139,5.8],[0,138.7,8.6],[0,87.1,57.7],[0,13.1,122.7]],8,8,8,8,8,8,8,8,8,8,8,8]]],[0,"75Ulh/hdBIbZB5E/DLzvLq",1,0],[5,318,298],[96.757,-161.03,0,0,0,0,1,1,1,1]],[18,"playerHead",1,[-29,-30,-31,-32,-33,-34],[[9,false,false,false,"{\"0\":{\"cc.Node\":{\"x\":-587.268,\"y\":309.644}},\"1\":{\"cc.Node\":{\"x\":-294.676,\"y\":579.022}}}",-28]],[0,"83jiZa1tZBALNG8rw6weAN",1,0],[5,70,70],[-587.268,309.644,0,0,0,0,1,1,1,1]],[8,"ui_btnRoomType_1",[-36,-37,-38,-39,-40],[[12,-35,[[[0,-7.4,122.4],[0,-137.6,9],[0,-137.6,-7.3],[0,-7.7,-118.9],[0,6.6,-117.4],[0,71.2,-64.1],[0,137.9,-5.5],[0,138.7,6.9],[0,139,5.8],[0,138.7,8.6],[0,87.1,57.7],[0,13.1,122.7]],8,8,8,8,8,8,8,8,8,8,8,8]]],[0,"93BwNQDLNCwroVx3Pm9hI0",1,0],[5,305,265],[132.73,149.118,0,0,0,0,1,1,1,1]],[8,"ui_btnRoomType_2",[-43,-44,-45,-46],[[3,-41,[31],32],[12,-42,[[[0,-7.4,122.4],[0,-137.6,9],[0,-137.6,-7.3],[0,-7.7,-118.9],[0,6.6,-117.4],[0,71.2,-64.1],[0,137.9,-5.5],[0,138.7,6.9],[0,139,5.8],[0,138.7,8.6],[0,87.1,57.7],[0,13.1,122.7]],8,8,8,8,8,8,8,8,8,8,8,8]]],[0,"d8X0cpDwdPK5WFApKNMCY+",1,0],[5,314,270],[-37.953,3.63,0,0,0,0,1,1,1,1]],[21,"ui_tioRight",1,[-49,-50,-51,-52],[[9,false,false,false,"{\"0\":{\"cc.Node\":{\"x\":604.93,\"y\":311.49,\"anchorX\":1},\"cc.Layout\":{\"type\":1,\"resizeMode\":1}},\"1\":{\"cc.Node\":{\"x\":327.243,\"y\":575.582,\"anchorX\":1},\"cc.Layout\":{\"type\":1,\"resizeMode\":1}}}",-47],[30,1,1,-48,[5,332,100]]],[0,"b6JK3Hp7dEZKT4LCT01Lw2",1,0],[5,332,100],[0,1,0.5],[604.93,311.49,0,0,0,0,1,1,1,1]],[22,"ui_btnPanel",1,[5,6,2,3],[[9,false,false,false,"{\"0\":{\"cc.Node\":{}},\"1\":{\"cc.Node\":{\"x\":-170.681,\"y\":-139.953}}}",-53]],[0,"d24OfKqqdGcaS5l7OzQxIf",1,0]],[13,"ui_bg",false,1,[[3,-54,[0],1],[27,false,false,"{\"0\":{\"cc.Node\":{\"active\":false},\"cc.Sprite\":{\"spriteFrame\":{\"uuid\":\"b568b72a-c85a-43c0-8993-869abc1dcb00\",\"bundle\":\"game_197001001\"}}},\"1\":{\"cc.Node\":{\"active\":false},\"cc.Sprite\":{\"spriteFrame\":{\"uuid\":\"9cad1f73-64ad-48ed-9c90-9e63c1974661\",\"bundle\":\"game_197001001\"}}}}",-55]],[0,"b5W0gpv31PR7K8UisuwkkE",1,0],[5,1280,720]],[1,"ui_btnHelp",7,[[3,-56,[11],12],[10,0.85,3,-57]],[0,"06ytKAuulJqoCYjA6SBVkf",1,0],[5,83,83],[-290.5,0,0,0,0,0,1,1,1,0]],[1,"ui_btnSetting",7,[[3,-58,[13],14],[10,0.85,3,-59]],[0,"a9rs3jPfpJqbig8hyUFx5v",1,0],[5,83,83],[-207.5,0,0,0,0,0,1,1,1,0]],[1,"ui_btnBack",7,[[3,-60,[15],16],[10,0.85,3,-61]],[0,"ebiVc+CFdKOqH6gZ/Gby34",1,0],[5,83,83],[-124.5,0,0,0,0,0,1,1,1,0]],[1,"ui_btnReport",7,[[3,-62,[17],18],[10,0.85,3,-63]],[0,"58aFTj+tRNVI31ARKr7ltv",1,0],[5,83,83],[-41.5,0,0,0,0,0,1,1,1,0]],[1,"ui_icon",5,[[6,-64,[23]],[11,true,"textures/lang/&/lang","cjc",-65,[[2,"vi",0.7,[0,0,-8.811]],[2,"pt",0.65,[0,0,-8.811]],[2,"ja",0.6,[0,0,-8.811]],[2,"id",0.6,[0,0,-8.811]]]]],[0,"dbQm01Bo9ERJLDI3rjUgbE",1,0],[5,148,57],[0,-8.811,0,0,0,0,1,1,1,1]],[1,"ui_icon",6,[[6,-66,[28]],[11,true,"textures/lang/&/lang","zjc",-67,[[2,"vi",0.55,[0,0,-8.811]],[2,"pt",0.5,[0,0,-8.811]],[2,"id",0.5,[0,0,-8.811]]]]],[0,"601MEuS2tOvp1qAMVvnV/d",1,0],[5,148,57],[0,-8.811,0,0,0,0,1,1,1,1]],[1,"ui_icon",2,[[6,-68,[37]],[11,true,"textures/lang/&/lang","zzc",-69,[[2,"vi",0.65,[0,0,-45.368]],[2,"pt",0.7,[0,0,-45.368]],[2,"ja",0.7,[0,0,-45.368]],[2,"id",0.7,[0,0,-45.368]]]]],[0,"56XOycznVF9aRmCWllmKKQ",1,0],[5,148,57],[0,-45.368,0,0,0,0,1,1,1,1]],[23,"ui_mask",false,2,[-71],[[3,-70,[41],42]],[0,"a9VC4G01BEv705wRIvGK/O",1,0],[5,374,376],[0,7,0,0,0,0,1,1,1,1]],[4,"ui_icon",17,[[6,-72,[40]],[15,true,"textures/lang/&/lang","suo",["zh","en"],-73]],[0,"34SQYDkMBOTr30QyjzEApl",1,0],[5,149,94]],[1,"ui_icon",3,[[6,-74,[47]],[11,true,"textures/lang/&/lang","gjc",-75,[[2,"vi",0.56,[0,0,-37.841]],[2,"pt",0.65,[0,0,-37.841]],[2,"ja",0.65,[0,0,-37.841]],[2,"id",0.7,[0,0,-37.841]]]]],[0,"f43rXd2rhFTa2L2PYz+om4",1,0],[5,148,57],[0,-37.841,0,0,0,0,1,1,1,1]],[24,"ui_mask",false,3,[-77],[[3,-76,[51],52]],[0,"c5HCJOj1RF0ZEMIsJYe9kS",1,0],[5,292,274]],[4,"ui_icon",20,[[6,-78,[50]],[15,true,"textures/lang/&/lang","suo",["zh","en"],-79]],[0,"aez7M5qOVOipWQa4mhOe/m",1,0],[5,149,94]],[1,"ddz_logo",1,[[7,"default","animation",0,false,"animation",-80,[53],54],[9,false,false,false,"{\"0\":{\"cc.Node\":{\"x\":489.604,\"y\":-269.036,\"scaleX\":0.7,\"scaleY\":0.7}},\"1\":{\"cc.Node\":{\"x\":219.278,\"y\":-540.877,\"scaleX\":0.7,\"scaleY\":0.7}}}",-81]],[0,"3148OICbhNN7ISNi1pTSrB",1,0],[5,500,300],[489.604,-269.036,0,0,0,0,1,0.7,0.7,1]],[1,"hg",1,[[7,"default","animation",0,false,"animation",-82,[55],56],[28,false,false,"{\"0\":{\"cc.Node\":{\"x\":-396.138}},\"1\":{\"cc.Node\":{\"x\":-396.138,\"active\":false}}}",-83]],[0,"caRnr2coVPBodri6W2SMOd",1,0],[5,488.4250793457031,627.0142211914062],[-396.138,0,0,0,0,0,1,1,1,1]],[4,"sp",4,[[25,0,-84,[2],3]],[0,"66AY2SXZtJ9JRn1RqJQOyz",1,0],[5,70,70]],[4,"head",4,[[26,0,-85,[4]]],[0,"88REXhmnNNXaWwFwngFJJJ",1,0],[5,70,70]],[1,"BG_money",4,[[3,-86,[5],6]],[0,"cdnjqJU35JKL4kno6tHgf5",1,0],[5,185,36],[140.267,-18.887,0,0,0,0,1,1,1,1]],[1,"icon_gold",4,[[3,-87,[7],8]],[0,"cfrpBtns5Is6L+wqfY6pWP",1,0],[5,33,36],[68.928,-20.609,0,0,0,0,1,1,1,1]],[19,"name",4,[[14,"我是地主大亨",24,26,false,1,2,-88,[9]]],[0,"1bMY8S7XJMYKy7RWTEOaRm",1,0],[5,210,32.76],[0,0,0.5],[47.049,22.934,0,0,0,0,1,1,1,1]],[20,"balance",4,[[14,"2000.00",30,32,false,1,2,-89,[10]]],[0,"99VsjBBXlPgZ1v9tAnAczN",1,0],[4,4280679423],[5,130,32],[0,0,0.5],[84.662,-18.484,0,0,0,0,1,1,1,1]],[4,"ui_img",5,[[3,-90,[19],20]],[0,"778KUIWYFDU6+igj0RV+ve",1,0],[5,305,265]],[4,"ui_ani",5,[[7,"default","animation",0,false,"animation",-91,[21],22]],[0,"e5V5tnFPdBGI5ottWmooJt",1,0],[5,316.6532287597656,277.5602111816406]],[1,"antes",5,[[5,"底注：2.33",20,22,false,1,1,2,-92,[24]]],[0,"03788XMTtEpbuJfqYlPqPC",1,0],[5,80,27.72],[0,-50.47,0,0,0,0,1,1,1,1]],[1,"access",5,[[5,"准入：2.33",20,22,false,1,1,2,-93,[25]]],[0,"famhB8E2VBgK8f4q2kUAZ/",1,0],[5,80,27.72],[0,-76.015,0,0,0,0,1,1,1,1]],[4,"ui_ani",6,[[7,"default","blue",0,false,"blue",-94,[26],27]],[0,"1bSYMRiuVNBqfTwEhAdS94",1,0],[5,328.46,285.02]],[1,"antes",6,[[5,"底注：2.33",20,22,false,1,1,2,-95,[29]]],[0,"daJNqY4IFN27klid2WDYB9",1,0],[5,80,27.72],[0,-52.93,0,0,0,0,1,1,1,1]],[1,"access",6,[[5,"准入：2.33",20,22,false,1,1,2,-96,[30]]],[0,"18WFkGD4tFGpaIjDmms6zp",1,0],[5,80,27.72],[0,-78.475,0,0,0,0,1,1,1,1]],[4,"ui_ani",2,[[7,"default","yellow",0,false,"yellow",-97,[33],34]],[0,"efzWk3dFRJ4JEPlMV/A178",1,0],[5,400,513.77]],[13,"ui_img",false,2,[[3,-98,[35],36]],[0,"c333XujslNuJnPHM75Onq+",1,0],[5,400,390]],[1,"antes",2,[[5,"底注：2.33",20,22,false,1,1,2,-99,[38]]],[0,"c052WfrrJCwKBxDi0qTJbi",1,0],[5,80,27.72],[0,-114.411,0,0,0,0,1,1,1,1]],[1,"access",2,[[5,"准入：2.33",20,22,false,1,1,2,-100,[39]]],[0,"62Oz5//kNNBrSEqogmGuCu",1,0],[5,80,27.72],[0,-139.956,0,0,0,0,1,1,1,1]],[1,"ui_ani",3,[[7,"default","animation",0,false,"animation",-101,[43],44]],[0,"d2EtbWrJpFqYDtmIoQcN+5",1,0],[5,355.3528747558594,290.1939697265625],[0,-12,0,0,0,0,1,1,1,1]],[4,"ui_img",3,[[3,-102,[45],46]],[0,"88kRiR8c9GRYe+ibOgKCPM",1,0],[5,318,298]],[1,"antes",3,[[5,"底注：2.33",20,22,false,1,1,2,-103,[48]]],[0,"86IDcOxoxN9bFzbn4dbpHx",1,0],[5,80,27.72],[0,-72.226,0,0,0,0,1,1,1,1]],[1,"access",3,[[5,"准入：2.33",20,22,false,1,1,2,-104,[49]]],[0,"cfmKkboUZNRYbQWJkyiypK",1,0],[5,80,27.72],[0,-97.771,0,0,0,0,1,1,1,1]]],0,[0,6,1,0,-1,5,0,-2,6,0,-3,3,0,-4,2,0,0,1,0,0,1,0,-1,9,0,-2,4,0,-3,7,0,-4,8,0,-5,22,0,-6,23,0,0,2,0,-1,37,0,-2,38,0,-3,16,0,-4,39,0,-5,40,0,-6,17,0,0,3,0,-1,41,0,-2,42,0,-3,19,0,-4,43,0,-5,44,0,-6,20,0,0,4,0,-1,24,0,-2,25,0,-3,26,0,-4,27,0,-5,28,0,-6,29,0,0,5,0,-1,30,0,-2,31,0,-3,14,0,-4,32,0,-5,33,0,0,6,0,0,6,0,-1,34,0,-2,15,0,-3,35,0,-4,36,0,0,7,0,0,7,0,-1,10,0,-2,11,0,-3,12,0,-4,13,0,0,8,0,0,9,0,0,9,0,0,10,0,0,10,0,0,11,0,0,11,0,0,12,0,0,12,0,0,13,0,0,13,0,0,14,0,0,14,0,0,15,0,0,15,0,0,16,0,0,16,0,0,17,0,-1,18,0,0,18,0,0,18,0,0,19,0,0,19,0,0,20,0,-1,21,0,0,21,0,0,21,0,0,22,0,0,22,0,0,23,0,0,23,0,0,24,0,0,25,0,0,26,0,0,27,0,0,28,0,0,29,0,0,30,0,0,31,0,0,32,0,0,33,0,0,34,0,0,35,0,0,36,0,0,37,0,0,38,0,0,39,0,0,40,0,0,41,0,0,42,0,0,43,0,0,44,0,7,1,2,3,8,3,3,8,5,3,8,6,3,8,104],[0,0,0,0,0,0,0,0,0,0,0,0,0,0,0,0,0,0,0,0,0,0,0,0,0,0,0,0,0,0,0,0,0,0,0,0,0,0,0,0,0,0,0,0,0,0,0,0,0,0,0,0,0,0,0,0,0,0,0],[-1,1,-1,1,-1,-1,1,-1,1,-1,-1,-1,1,-1,1,-1,1,-1,1,-1,1,-1,2,-1,-1,-1,-1,2,-1,-1,-1,-1,1,-1,2,-1,1,-1,-1,-1,-1,-1,1,-1,2,-1,1,-1,-1,-1,-1,-1,1,-1,2,-1,2,4,5],[0,2,0,3,0,0,4,0,5,0,0,0,6,0,7,0,8,0,9,0,10,1,11,0,0,0,1,12,0,0,0,0,13,1,14,0,15,0,0,0,0,0,16,1,17,0,18,0,0,0,0,0,19,1,20,1,21,2,22]]